odoo9_addon_sale_open_qty-9.0.1.0.1-nspkg.pth
odoo_addons/sale_open_qty/README.rst
odoo_addons/sale_open_qty/__init__.py
odoo_addons/sale_open_qty/__openerp__.py
odoo_addons/sale_open_qty/init_hook.py
odoo_addons/sale_open_qty/i18n/sale_open_qty.pot
odoo_addons/sale_open_qty/models/__init__.py
odoo_addons/sale_open_qty/models/sale_order.py
odoo_addons/sale_open_qty/static/description/icon.png
odoo_addons/sale_open_qty/tests/__init__.py
odoo_addons/sale_open_qty/tests/test_sale_open_qty.py
odoo_addons/sale_open_qty/views/sale_view.xml
odoo9_addon_sale_open_qty-9.0.1.0.1.dist-info/METADATA
odoo9_addon_sale_open_qty-9.0.1.0.1.dist-info/WHEEL
odoo9_addon_sale_open_qty-9.0.1.0.1.dist-info/namespace_packages.txt
odoo9_addon_sale_open_qty-9.0.1.0.1.dist-info/top_level.txt
odoo9_addon_sale_open_qty-9.0.1.0.1.dist-info/RECORD
