Metadata-Version: 2.1
Name: odoo9-addon-sale-open-qty
Version: 9.0.1.0.1
Summary: Allows to identify the sale orders that have quantities pending to invoice or to deliver.
Home-page: https://github.com/OCA/sale-workflow
Author: Eficent, Odoo Community Association (OCA)
Author-email: support@odoo-community.org
License: AGPL-3
Platform: UNKNOWN
Classifier: Programming Language :: Python
Classifier: Framework :: Odoo
Classifier: License :: OSI Approved :: GNU Affero General Public License v3
Requires-Python: ~=2.7
Requires-Dist: odoo (<9.1a,>=9.0a)
